eaot/__init__.py
eaot-0.0.1.dist-info/LICENSE
eaot-0.0.1.dist-info/WHEEL
eaot-0.0.1.dist-info/METADATA
eaot-0.0.1.dist-info/RECORD
